[
  {
    "Type": "FortQuestDefinitionComponent_DisplaySettings",
    "Name": "FortQuestDefinitionComponent_DisplaySettings_0",
    "Outer": "HalloweenQuest_KillVlad",
    "Class": "UScriptClass'FortQuestDefinitionComponent_DisplaySettings'",
    "Flags": "RF_Transactional | RF_WasLoaded | RF_LoadCompleted",
    "Properties": {
      "InformationSettings": {
        "CompletionText": {
          "Namespace": "",
          "Key": "F7C02FCC4FFEE2EA976DED93557ACB7F",
          "SourceString": "Vlad eliminated!",
          "LocalizedString": "Vlad eliminated!"
        }
      }
    }
  },
  {
    "Type": "FortQuestItemDefinition_Campaign",
    "Name": "HalloweenQuest_KillVlad",
    "Class": "UScriptClass'FortQuestItemDefinition_Campaign'",
    "Flags": "RF_Public | RF_Standalone | RF_Transactional | RF_WasLoaded | RF_LoadCompleted",
    "Properties": {
      "QuestType": "EFortQuestType::Optional",
      "RewardsTable": {
        "ObjectName": "DataTable'QuestRewards'",
        "ObjectPath": "/Game/Quests/QuestRewards.0"
      },
      "Objectives": [
        {
          "BackendName": "kill_miniboss_vlad",
          "ItemEvent": "EFortQuestObjectiveItemEvent::Max_None",
          "bHidden": false,
          "bRequirePrimaryMissionCompletion": false,
          "bCanProgressInZone": true,
          "bDisplayDynamicAnnouncementUpdate": false,
          "DynamicStatusUpdateType": "EObjectiveStatusUpdateType::Always",
          "LinkToItemManagement": "EFortFrontendInventoryFilter::Max_None",
          "ObjectiveFilters": [],
          "InlineObjectiveStats": [],
          "ObjectiveStatHandle": {
            "DataTable": {
              "ObjectName": "DataTable'ObjectiveStatTable'",
              "ObjectPath": "/Game/Quests/ObjectiveStatTable.0"
            },
            "RowName": "kill_miniboss_vlad"
          },
          "AlternativeStatHandles": [],
          "ItemReference": {
            "AssetPathName": "",
            "SubPathString": ""
          },
          "ItemTemplateIdOverride": "",
          "LinkSquadID": "None",
          "LinkSquadIndex": 0,
          "Description": {
            "Namespace": "",
            "Key": "4A45211746BCD3F15633FAACE339E92E",
            "SourceString": "Eliminate Vlad ",
            "LocalizedString": "Eliminate Vlad "
          },
          "HudShortDescription": {
            "Namespace": "",
            "Key": "58E261814F2672A3CE7A068F06B4ED35",
            "SourceString": "Vlad eliminated",
            "LocalizedString": "Vlad eliminated"
          },
          "ObjectiveConversations": [],
          "ObjectiveDisplayInfo": {
            "DisplayStage": 0,
            "DisplayMaxStage": 0
          },
          "Count": 1,
          "Stage": -1,
          "DynamicStatusUpdatePercentInterval": 25,
          "DynamicUpdateCompletionDelay": 0.2,
          "ScriptedAction": {
            "AssetPathName": "",
            "SubPathString": ""
          },
          "FrontendScriptedAction": {
            "AssetPathName": "",
            "SubPathString": ""
          }
        }
      ],
      "Category": {
        "DataTable": {
          "ObjectName": "DataTable'QuestCategoryTable'",
          "ObjectPath": "/Game/Quests/QuestCategoryTable.0"
        },
        "RowName": "LTE_Fortnitemares"
      },
      "SortPriority": 70,
      "QuestDefinitionComponents": [
        {
          "ObjectName": "FortQuestDefinitionComponent_DisplaySettings'HalloweenQuest_KillVlad:FortQuestDefinitionComponent_DisplaySettings_0'",
          "ObjectPath": "/SaveTheWorld/Quests/Events/Halloween/HalloweenQuest_KillVlad.0"
        }
      ],
      "ItemName": {
        "Namespace": "",
        "Key": "89992BFA482D7F8A9EC8ADB0778C63E0",
        "SourceString": "Stakeout",
        "LocalizedString": "Stakeout"
      },
      "ItemDescription": {
        "Namespace": "",
        "Key": "CA40E040406152C7EF9B6596C0EF6990",
        "SourceString": "Find and destroy Storm's recreation of the ancient Hexsylvanian tyrant!  Hint: Cannot be completed in the Haunted Hotel.",
        "LocalizedString": "Find and destroy Storm's recreation of the ancient Hexsylvanian tyrant!  Hint: Cannot be completed in the Haunted Hotel."
      },
      "DataList": [
        {
          "Icon": {
            "AssetPathName": "/Game/UI/Foundation/Textures/Icons/Mission/T-Icon-Miniboss-128.T-Icon-Miniboss-128",
            "SubPathString": ""
          }
        }
      ]
    }
  }
]