[
  {
    "Type": "FortQuestDefinitionComponent_DisplaySettings",
    "Name": "FortQuestDefinitionComponent_DisplaySettings_0",
    "Outer": "StormQuest_2018_CompleteSurvive7Day_D1",
    "Class": "UScriptClass'FortQuestDefinitionComponent_DisplaySettings'",
    "Flags": "RF_Transactional | RF_WasLoaded | RF_LoadCompleted",
    "Properties": {
      "InformationSettings": {
        "CompletionText": {
          "Namespace": "",
          "Key": "5C29C0FF43FC11B491126EB10B2C44CC",
          "SourceString": "You have survived!",
          "LocalizedString": "You have survived!"
        }
      }
    }
  },
  {
    "Type": "FortQuestItemDefinition_Campaign",
    "Name": "StormQuest_2018_CompleteSurvive7Day_D1",
    "Class": "UScriptClass'FortQuestItemDefinition_Campaign'",
    "Flags": "RF_Public | RF_Standalone | RF_Transactional | RF_WasLoaded | RF_LoadCompleted",
    "Properties": {
      "QuestType": "EFortQuestType::Optional",
      "RewardsTable": {
        "ObjectName": "DataTable'QuestRewards'",
        "ObjectPath": "/Game/Quests/QuestRewards.0"
      },
      "Objectives": [
        {
          "BackendName": "complete_survivalmode_pve01_7day",
          "ItemEvent": "EFortQuestObjectiveItemEvent::Max_None",
          "bHidden": false,
          "bRequirePrimaryMissionCompletion": false,
          "bCanProgressInZone": false,
          "bDisplayDynamicAnnouncementUpdate": false,
          "DynamicStatusUpdateType": "EObjectiveStatusUpdateType::Never",
          "LinkToItemManagement": "EFortFrontendInventoryFilter::Max_None",
          "ObjectiveFilters": [],
          "InlineObjectiveStats": [],
          "ObjectiveStatHandle": {
            "DataTable": {
              "ObjectName": "DataTable'ObjectiveStatTable'",
              "ObjectPath": "/Game/Quests/ObjectiveStatTable.0"
            },
            "RowName": "complete_survivalmode_pve01_7day"
          },
          "AlternativeStatHandles": [],
          "ItemReference": {
            "AssetPathName": "",
            "SubPathString": ""
          },
          "ItemTemplateIdOverride": "",
          "LinkSquadID": "None",
          "LinkSquadIndex": 0,
          "Description": {
            "Namespace": "",
            "Key": "2D78524B496EF640D892008FE6A191A0",
            "SourceString": "Complete a 7 Day Survive the Storm in a [UIRating] zone",
            "LocalizedString": "Complete a 7 Day Survive the Storm in a [UIRating] zone"
          },
          "HudShortDescription": {
            "CultureInvariantString": null
          },
          "ObjectiveConversations": [],
          "ObjectiveDisplayInfo": {
            "DisplayStage": 0,
            "DisplayMaxStage": 0
          },
          "Count": 1,
          "Stage": 0,
          "DynamicStatusUpdatePercentInterval": 25,
          "DynamicUpdateCompletionDelay": 0.0,
          "ScriptedAction": {
            "AssetPathName": "",
            "SubPathString": ""
          },
          "FrontendScriptedAction": {
            "AssetPathName": "",
            "SubPathString": ""
          }
        }
      ],
      "Category": {
        "DataTable": {
          "ObjectName": "DataTable'QuestCategoryTable'",
          "ObjectPath": "/Game/Quests/QuestCategoryTable.0"
        },
        "RowName": "LTE_Storm2018"
      },
      "SortPriority": 80,
      "QuestDefinitionComponents": [
        {
          "ObjectName": "FortQuestDefinitionComponent_DisplaySettings'StormQuest_2018_CompleteSurvive7Day_D1:FortQuestDefinitionComponent_DisplaySettings_0'",
          "ObjectPath": "/SaveTheWorld/Quests/Events/Storm2018/StormQuest_2018_CompleteSurvive7Day_D1.0"
        }
      ],
      "ItemName": {
        "Namespace": "",
        "Key": "EBCAC93644EA0CE515E684B3C3F3B3E6",
        "SourceString": "Against All Odds",
        "LocalizedString": "Against All Odds"
      },
      "ItemDescription": {
        "Namespace": "",
        "Key": "34E0EE6A4922822B334543AF03A79B14",
        "SourceString": "Survive the Storm for 7 days in a Power 15 zone.\r\n\r\nYou can access Survive the Storm by selecting the Map tab and then selecting the Survive the Storm pin.",
        "LocalizedString": "Survive the Storm for 7 days in a Power 15 zone.\r\n\r\nYou can access Survive the Storm by selecting the Map tab and then selecting the Survive the Storm pin."
      },
      "DataList": [
        {
          "Icon": {
            "AssetPathName": "/SaveTheWorld/UI/Foundation/Textures/Icons/Mission/T-Icon-Survival7-128.T-Icon-Survival7-128",
            "SubPathString": ""
          }
        }
      ]
    }
  }
]