[
  {
    "Type": "FortQuestDefinitionComponent_DisplaySettings",
    "Name": "FortQuestDefinitionComponent_DisplaySettings_0",
    "Outer": "CannyValleyQuest_Filler_1_D4",
    "Class": "UScriptClass'FortQuestDefinitionComponent_DisplaySettings'",
    "Flags": "RF_Transactional | RF_WasLoaded | RF_LoadCompleted",
    "Properties": {
      "InformationSettings": {
        "CompletionText": {
          "Namespace": "",
          "Key": "39850E3840CEE1B7D164F7BB24AAEDC4",
          "SourceString": "Mimics destroyed.",
          "LocalizedString": "Mimics destroyed."
        }
      }
    }
  },
  {
    "Type": "FortQuestItemDefinition_Campaign",
    "Name": "CannyValleyQuest_Filler_1_D4",
    "Class": "UScriptClass'FortQuestItemDefinition_Campaign'",
    "Flags": "RF_Public | RF_Standalone | RF_Transactional | RF_WasLoaded | RF_LoadCompleted",
    "Properties": {
      "QuestType": "EFortQuestType::Optional",
      "RewardsTable": {
        "ObjectName": "DataTable'QuestRewards'",
        "ObjectPath": "/Game/Quests/QuestRewards.0"
      },
      "Objectives": [
        {
          "BackendName": "complete_mimic_3_diff4",
          "ItemEvent": "EFortQuestObjectiveItemEvent::Max_None",
          "bHidden": false,
          "bRequirePrimaryMissionCompletion": true,
          "bCanProgressInZone": true,
          "bDisplayDynamicAnnouncementUpdate": false,
          "DynamicStatusUpdateType": "EObjectiveStatusUpdateType::Always",
          "LinkToItemManagement": "EFortFrontendInventoryFilter::Max_None",
          "ObjectiveFilters": [],
          "InlineObjectiveStats": [],
          "ObjectiveStatHandle": {
            "DataTable": {
              "ObjectName": "DataTable'ObjectiveStatTable'",
              "ObjectPath": "/Game/Quests/ObjectiveStatTable.0"
            },
            "RowName": "complete_mimic_3_diff4"
          },
          "AlternativeStatHandles": [],
          "ItemReference": {
            "AssetPathName": "",
            "SubPathString": ""
          },
          "ItemTemplateIdOverride": "",
          "LinkSquadID": "None",
          "LinkSquadIndex": 0,
          "Description": {
            "Namespace": "",
            "Key": "289F6BFE4EA682419FCF679B07BD723F",
            "SourceString": "Destroy 2 Mimics in successful missions in a [UIRating]+ zone",
            "LocalizedString": "Destroy 2 Mimics in successful missions in a [UIRating]+ zone"
          },
          "HudShortDescription": {
            "Namespace": "",
            "Key": "DE33C44D4803AA31667D61B194BDB541",
            "SourceString": "Mimics destroyed",
            "LocalizedString": "Mimics destroyed"
          },
          "ObjectiveConversations": [],
          "ObjectiveDisplayInfo": {
            "DisplayStage": 0,
            "DisplayMaxStage": 0
          },
          "Count": 2,
          "Stage": -1,
          "DynamicStatusUpdatePercentInterval": 25,
          "DynamicUpdateCompletionDelay": 0.0,
          "ScriptedAction": {
            "AssetPathName": "",
            "SubPathString": ""
          },
          "FrontendScriptedAction": {
            "AssetPathName": "",
            "SubPathString": ""
          }
        }
      ],
      "Category": {
        "DataTable": {
          "ObjectName": "DataTable'QuestCategoryTable'",
          "ObjectPath": "/Game/Quests/QuestCategoryTable.0"
        },
        "RowName": "SideQuests"
      },
      "QuestDefinitionComponents": [
        {
          "ObjectName": "FortQuestDefinitionComponent_DisplaySettings'CannyValleyQuest_Filler_1_D4:FortQuestDefinitionComponent_DisplaySettings_0'",
          "ObjectPath": "/SaveTheWorld/Quests/CannyValley/CannyValleyQuest_Filler_1_D4.0"
        }
      ],
      "ItemName": {
        "Namespace": "",
        "Key": "5FF3BB284599CBC85AFE4A89422BB6D1",
        "SourceString": "Please Stand Up...",
        "LocalizedString": "Please Stand Up..."
      },
      "ItemDescription": {
        "Namespace": "",
        "Key": "E9D401E74384F5A72BA272A2728195B4",
        "SourceString": "Mimics keep ruining treasure for the good people. Find and kill 2 mimics.",
        "LocalizedString": "Mimics keep ruining treasure for the good people. Find and kill 2 mimics."
      },
      "DataList": [
        {
          "Icon": {
            "AssetPathName": "/Game/UI/Foundation/Textures/Icons/Social/T-Icon-Quest-Journal-64.T-Icon-Quest-Journal-64",
            "SubPathString": ""
          }
        }
      ]
    }
  }
]