[
  {
    "Type": "ArrowComponent",
    "Name": "ArrowComponent_0",
    "Outer": "Trap_Rail_Turret_C",
    "Class": "UScriptClass'ArrowComponent'",
    "Flags": "RF_Public | RF_Transactional | RF_ArchetypeObject | RF_WasLoaded | RF_LoadCompleted",
    "Properties": {
      "RelativeLocation": {
        "X": 0.0,
        "Y": 100.0,
        "Z": 130.0
      },
      "RelativeRotation": {
        "Pitch": 0.0,
        "Yaw": 89.99988,
        "Roll": -0.0
      }
    }
  },
  {
    "Type": "AthenaTrapAIPerceptionStimuliSourceComponent",
    "Name": "Trap AI Perception Stimuli Source Component",
    "Outer": "Default__Trap_Rail_Turret_C",
    "Class": "UScriptClass'AthenaTrapAIPerceptionStimuliSourceComponent'",
    "Flags": "RF_Public | RF_Transactional | RF_ArchetypeObject | RF_DefaultSubObject | RF_WasLoaded | RF_LoadCompleted"
  },
  {
    "Type": "BaseBuildingStaticMeshComponent",
    "Name": "StaticMeshComponent0",
    "Outer": "Default__Trap_Rail_Turret_C",
    "Class": "UScriptClass'BaseBuildingStaticMeshComponent'",
    "Flags": "RF_Public | RF_Transactional | RF_ArchetypeObject | RF_DefaultSubObject | RF_WasLoaded | RF_LoadCompleted",
    "Properties": {
      "StaticMesh": {
        "ObjectName": "StaticMesh'Electric_Trap_Wall'",
        "ObjectPath": "/SaveTheWorld/Weapons/FORT_TRAPS/Wall_Electric_Trap/Mesh/Electric_Trap_Wall.1"
      },
      "bAffectDistanceFieldLighting": false,
      "BodyInstance": {
        "CollisionEnabled": "ECollisionEnabled::QueryOnly",
        "CollisionProfileName": "Custom",
        "CollisionResponses": {
          "ResponseArray": [
            {
              "Channel": "WorldStatic",
              "Response": "ECollisionResponse::ECR_Ignore"
            },
            {
              "Channel": "WorldDynamic",
              "Response": "ECollisionResponse::ECR_Ignore"
            },
            {
              "Channel": "Pawn",
              "Response": "ECollisionResponse::ECR_Ignore"
            },
            {
              "Channel": "Visibility",
              "Response": "ECollisionResponse::ECR_Overlap"
            },
            {
              "Channel": "Camera",
              "Response": "ECollisionResponse::ECR_Ignore"
            },
            {
              "Channel": "PhysicsBody",
              "Response": "ECollisionResponse::ECR_Ignore"
            },
            {
              "Channel": "Vehicle",
              "Response": "ECollisionResponse::ECR_Ignore"
            },
            {
              "Channel": "Destructible",
              "Response": "ECollisionResponse::ECR_Ignore"
            },
            {
              "Channel": "EngineTraceChannel2",
              "Response": "ECollisionResponse::ECR_Ignore"
            },
            {
              "Channel": "EngineTraceChannel3",
              "Response": "ECollisionResponse::ECR_Ignore"
            },
            {
              "Channel": "EngineTraceChannel4",
              "Response": "ECollisionResponse::ECR_Ignore"
            },
            {
              "Channel": "EngineTraceChannel5",
              "Response": "ECollisionResponse::ECR_Ignore"
            },
            {
              "Channel": "EngineTraceChannel6",
              "Response": "ECollisionResponse::ECR_Ignore"
            },
            {
              "Channel": "FCC_Trace_WeaponWorldMulti",
              "Response": "ECollisionResponse::ECR_Ignore"
            },
            {
              "Channel": "FCC_Object_NoGhost",
              "Response": "ECollisionResponse::ECR_Ignore"
            },
            {
              "Channel": "FCC_Object_Water",
              "Response": "ECollisionResponse::ECR_Ignore"
            }
          ]
        },
        "bAutoWeld": false
      },
      "OnComponentPhysicsStateChanged": {
        "InvocationList": [
          {
            "Object": {
              "ObjectName": "Trap_Rail_Turret_C'Default__Trap_Rail_Turret_C'",
              "ObjectPath": "/SaveTheWorld/Items/Traps/Blueprints/Trap_Rail_Turret.21"
            },
            "FunctionName": "OnPhysicsStateChanged"
          }
        ]
      },
      "bCanEverAffectNavigation": true
    }
  },
  {
    "Type": "BlueprintGeneratedClass",
    "Name": "Trap_Rail_Turret_C",
    "Class": "UScriptClass'BlueprintGeneratedClass'",
    "Flags": "RF_Public | RF_Transactional | RF_WasLoaded | RF_LoadCompleted",
    "Properties": {
      "SimpleConstructionScript": {
        "ObjectName": "SimpleConstructionScript'Trap_Rail_Turret_C:SimpleConstructionScript_47'",
        "ObjectPath": "/SaveTheWorld/Items/Traps/Blueprints/Trap_Rail_Turret.19"
      },
      "UberGraphFunction": {
        "ObjectName": "Function'Trap_Rail_Turret_C:ExecuteUbergraph_Trap_Rail_Turret'",
        "ObjectPath": "/SaveTheWorld/Items/Traps/Blueprints/Trap_Rail_Turret.5"
      }
    },
    "SuperStruct": {
      "ObjectName": "Class'BuildingTrapWall'",
      "ObjectPath": "/Script/FortniteGame"
    },
    "Children": [
      {
        "ObjectName": "Function'Trap_Rail_Turret_C:OnPlaced'",
        "ObjectPath": "/SaveTheWorld/Items/Traps/Blueprints/Trap_Rail_Turret.8"
      },
      {
        "ObjectName": "Function'Trap_Rail_Turret_C:OnFinishedBuilding'",
        "ObjectPath": "/SaveTheWorld/Items/Traps/Blueprints/Trap_Rail_Turret.6"
      },
      {
        "ObjectName": "Function'Trap_Rail_Turret_C:OnReloadEnd'",
        "ObjectPath": "/SaveTheWorld/Items/Traps/Blueprints/Trap_Rail_Turret.9"
      },
      {
        "ObjectName": "Function'Trap_Rail_Turret_C:OnOutOfDurability'",
        "ObjectPath": "/SaveTheWorld/Items/Traps/Blueprints/Trap_Rail_Turret.7"
      },
      {
        "ObjectName": "Function'Trap_Rail_Turret_C:ExecuteUbergraph_Trap_Rail_Turret'",
        "ObjectPath": "/SaveTheWorld/Items/Traps/Blueprints/Trap_Rail_Turret.5"
      }
    ],
    "ChildProperties": [
      {
        "Type": "StructProperty",
        "Name": "UberGraphFrame",
        "Flags": "RF_Public | RF_LoadCompleted",
        "ElementSize": 16,
        "PropertyFlags": "Transient | DuplicateTransient",
        "Struct": {
          "ObjectName": "Class'PointerToUberGraphFrame'",
          "ObjectPath": "/Script/Engine"
        }
      },
      {
        "Type": "ObjectProperty",
        "Name": "FireLocation",
        "Flags": "RF_Public | RF_LoadCompleted",
        "ElementSize": 8,
        "PropertyFlags": "BlueprintVisible | InstancedReference | NonTransactional",
        "PropertyClass": {
          "ObjectName": "Class'ArrowComponent'",
          "ObjectPath": "/Script/Engine"
        }
      },
      {
        "Type": "ObjectProperty",
        "Name": "Effect_Charge",
        "Flags": "RF_Public | RF_LoadCompleted",
        "ElementSize": 8,
        "PropertyFlags": "BlueprintVisible | InstancedReference | NonTransactional",
        "PropertyClass": {
          "ObjectName": "Class'ParticleSystemComponent'",
          "ObjectPath": "/Script/Engine"
        }
      },
      {
        "Type": "ObjectProperty",
        "Name": "TriggerComponent",
        "Flags": "RF_Public | RF_LoadCompleted",
        "ElementSize": 8,
        "PropertyFlags": "BlueprintVisible | InstancedReference | NonTransactional",
        "PropertyClass": {
          "ObjectName": "Class'BoxComponent'",
          "ObjectPath": "/Script/Engine"
        }
      },
      {
        "Type": "ObjectProperty",
        "Name": "Root",
        "Flags": "RF_Public | RF_LoadCompleted",
        "ElementSize": 8,
        "PropertyFlags": "BlueprintVisible | InstancedReference | NonTransactional",
        "PropertyClass": {
          "ObjectName": "Class'SceneComponent'",
          "ObjectPath": "/Script/Engine"
        }
      },
      {
        "Type": "ObjectProperty",
        "Name": "gun",
        "Flags": "RF_Public | RF_LoadCompleted",
        "ElementSize": 8,
        "PropertyFlags": "BlueprintVisible | InstancedReference | NonTransactional",
        "PropertyClass": {
          "ObjectName": "Class'StaticMeshComponent'",
          "ObjectPath": "/Script/Engine"
        }
      },
      {
        "Type": "ObjectProperty",
        "Name": "Activate_Sound_Cue",
        "Flags": "RF_Public | RF_LoadCompleted",
        "ElementSize": 8,
        "PropertyFlags": "Edit | BlueprintVisible",
        "PropertyClass": {
          "ObjectName": "Class'SoundCue'",
          "ObjectPath": "/Script/Engine"
        }
      },
      {
        "Type": "ObjectProperty",
        "Name": "Explode_Sound_Cue",
        "Flags": "RF_Public | RF_LoadCompleted",
        "ElementSize": 8,
        "PropertyFlags": "Edit | BlueprintVisible",
        "PropertyClass": {
          "ObjectName": "Class'SoundCue'",
          "ObjectPath": "/Script/Engine"
        }
      }
    ],
    "FuncMap": {
      "ExecuteUbergraph_Trap_Rail_Turret": {
        "ObjectName": "Function'Trap_Rail_Turret_C:ExecuteUbergraph_Trap_Rail_Turret'",
        "ObjectPath": "/SaveTheWorld/Items/Traps/Blueprints/Trap_Rail_Turret.5"
      },
      "OnOutOfDurability": {
        "ObjectName": "Function'Trap_Rail_Turret_C:OnOutOfDurability'",
        "ObjectPath": "/SaveTheWorld/Items/Traps/Blueprints/Trap_Rail_Turret.7"
      },
      "OnReloadEnd": {
        "ObjectName": "Function'Trap_Rail_Turret_C:OnReloadEnd'",
        "ObjectPath": "/SaveTheWorld/Items/Traps/Blueprints/Trap_Rail_Turret.9"
      },
      "OnFinishedBuilding": {
        "ObjectName": "Function'Trap_Rail_Turret_C:OnFinishedBuilding'",
        "ObjectPath": "/SaveTheWorld/Items/Traps/Blueprints/Trap_Rail_Turret.6"
      },
      "OnPlaced": {
        "ObjectName": "Function'Trap_Rail_Turret_C:OnPlaced'",
        "ObjectPath": "/SaveTheWorld/Items/Traps/Blueprints/Trap_Rail_Turret.8"
      }
    },
    "ClassFlags": "CLASS_Config | CLASS_CompiledFromBlueprint | CLASS_HasInstancedReference",
    "ClassWithin": {
      "ObjectName": "Class'Object'",
      "ObjectPath": "/Script/CoreUObject"
    },
    "ClassConfigName": "Game",
    "bCooked": true,
    "ClassDefaultObject": {
      "ObjectName": "Trap_Rail_Turret_C'Default__Trap_Rail_Turret_C'",
      "ObjectPath": "/SaveTheWorld/Items/Traps/Blueprints/Trap_Rail_Turret.21"
    },
    "EditorTags": {
      "BlueprintType": "BPTYPE_Normal"
    }
  },
  {
    "Type": "BoxComponent",
    "Name": "BoxComponent_126__FC5252EC",
    "Outer": "Trap_Rail_Turret_C",
    "Class": "UScriptClass'BoxComponent'",
    "Flags": "RF_Public | RF_Transactional | RF_ArchetypeObject | RF_WasLoaded | RF_LoadCompleted",
    "Properties": {
      "BoxExtent": {
        "X": 512.0,
        "Y": 512.0,
        "Z": 512.0
      },
      "bUseSystemDefaultObstacleAreaClass": false,
      "AreaClassOverride": {
        "ObjectName": "Class'FortMetaNavArea_Obstacles'",
        "ObjectPath": "/Script/FortniteAI"
      },
      "BodyInstance": {
        "CollisionProfileName": "Custom",
        "CollisionResponses": {
          "ResponseArray": [
            {
              "Channel": "WorldStatic",
              "Response": "ECollisionResponse::ECR_Ignore"
            },
            {
              "Channel": "Pawn",
              "Response": "ECollisionResponse::ECR_Overlap"
            },
            {
              "Channel": "Visibility",
              "Response": "ECollisionResponse::ECR_Ignore"
            },
            {
              "Channel": "Camera",
              "Response": "ECollisionResponse::ECR_Ignore"
            },
            {
              "Channel": "PhysicsBody",
              "Response": "ECollisionResponse::ECR_Ignore"
            },
            {
              "Channel": "Vehicle",
              "Response": "ECollisionResponse::ECR_Ignore"
            },
            {
              "Channel": "Destructible",
              "Response": "ECollisionResponse::ECR_Ignore"
            },
            {
              "Channel": "EngineTraceChannel2",
              "Response": "ECollisionResponse::ECR_Ignore"
            },
            {
              "Channel": "EngineTraceChannel3",
              "Response": "ECollisionResponse::ECR_Ignore"
            },
            {
              "Channel": "EngineTraceChannel4",
              "Response": "ECollisionResponse::ECR_Ignore"
            },
            {
              "Channel": "FCC_Object_PawnAI",
              "Response": "ECollisionResponse::ECR_Overlap"
            },
            {
              "Channel": "WorldDynamic",
              "Response": "ECollisionResponse::ECR_Ignore"
            },
            {
              "Channel": "FCC_Trace_WeaponWorldMulti",
              "Response": "ECollisionResponse::ECR_Ignore"
            }
          ]
        },
        "MassInKgOverride": 33356.074
      },
      "RelativeLocation": {
        "X": 0.0,
        "Y": 562.0,
        "Z": 132.0
      }
    }
  },
  {
    "Type": "Function",
    "Name": "ExecuteUbergraph_Trap_Rail_Turret",
    "Outer": "Trap_Rail_Turret_C",
    "Class": "UScriptClass'Function'",
    "Flags": "RF_Public | RF_WasLoaded | RF_LoadCompleted",
    "ChildProperties": [
      {
        "Type": "IntProperty",
        "Name": "EntryPoint",
        "Flags": "RF_Public",
        "ElementSize": 4,
        "PropertyFlags": "BlueprintVisible | BlueprintReadOnly | Parm"
      },
      {
        "Type": "BoolProperty",
        "Name": "CallFunc_IsValid_ReturnValue",
        "Flags": "RF_Public",
        "ElementSize": 1,
        "FieldSize": 1,
        "ByteOffset": 0,
        "ByteMask": 1,
        "FieldMask": 255,
        "BoolSize": 1,
        "bIsNativeBool": true
      },
      {
        "Type": "ObjectProperty",
        "Name": "CallFunc_SpawnEmitterAttached_ReturnValue",
        "Flags": "RF_Public",
        "ElementSize": 8,
        "PropertyFlags": "InstancedReference",
        "PropertyClass": {
          "ObjectName": "Class'ParticleSystemComponent'",
          "ObjectPath": "/Script/Engine"
        }
      },
      {
        "Type": "StructProperty",
        "Name": "CallFunc_K2_GetComponentLocation_ReturnValue",
        "Flags": "RF_Public",
        "ElementSize": 24,
        "Struct": {
          "ObjectName": "Class'Vector'",
          "ObjectPath": "/Script/CoreUObject"
        }
      },
      {
        "Type": "DoubleProperty",
        "Name": "CallFunc_BreakVector_X",
        "Flags": "RF_Public",
        "ElementSize": 8
      },
      {
        "Type": "DoubleProperty",
        "Name": "CallFunc_BreakVector_Y",
        "Flags": "RF_Public",
        "ElementSize": 8
      },
      {
        "Type": "DoubleProperty",
        "Name": "CallFunc_BreakVector_Z",
        "Flags": "RF_Public",
        "ElementSize": 8
      },
      {
        "Type": "StructProperty",
        "Name": "CallFunc_Multiply_VectorVector_ReturnValue",
        "Flags": "RF_Public",
        "ElementSize": 24,
        "Struct": {
          "ObjectName": "Class'Vector'",
          "ObjectPath": "/Script/CoreUObject"
        }
      },
      {
        "Type": "DoubleProperty",
        "Name": "CallFunc_Multiply_DoubleDouble_ReturnValue",
        "Flags": "RF_Public",
        "ElementSize": 8
      },
      {
        "Type": "DoubleProperty",
        "Name": "CallFunc_Multiply_DoubleDouble_ReturnValue_1",
        "Flags": "RF_Public",
        "ElementSize": 8
      },
      {
        "Type": "StructProperty",
        "Name": "CallFunc_MakeVector_ReturnValue",
        "Flags": "RF_Public",
        "ElementSize": 24,
        "Struct": {
          "ObjectName": "Class'Vector'",
          "ObjectPath": "/Script/CoreUObject"
        }
      },
      {
        "Type": "StructProperty",
        "Name": "CallFunc_MakeVector_ReturnValue_1",
        "Flags": "RF_Public",
        "ElementSize": 24,
        "Struct": {
          "ObjectName": "Class'Vector'",
          "ObjectPath": "/Script/CoreUObject"
        }
      },
      {
        "Type": "StructProperty",
        "Name": "CallFunc_Multiply_VectorVector_ReturnValue_1",
        "Flags": "RF_Public",
        "ElementSize": 24,
        "Struct": {
          "ObjectName": "Class'Vector'",
          "ObjectPath": "/Script/CoreUObject"
        }
      },
      {
        "Type": "StructProperty",
        "Name": "CallFunc_Multiply_VectorVector_ReturnValue_2",
        "Flags": "RF_Public",
        "ElementSize": 24,
        "Struct": {
          "ObjectName": "Class'Vector'",
          "ObjectPath": "/Script/CoreUObject"
        }
      },
      {
        "Type": "StructProperty",
        "Name": "K2Node_MakeStruct_ParticleSysParam",
        "Flags": "RF_Public",
        "ElementSize": 224,
        "Struct": {
          "ObjectName": "Class'ParticleSysParam'",
          "ObjectPath": "/Script/Engine"
        }
      },
      {
        "Type": "StructProperty",
        "Name": "K2Node_MakeStruct_ParticleSysParam_1",
        "Flags": "RF_Public",
        "ElementSize": 224,
        "Struct": {
          "ObjectName": "Class'ParticleSysParam'",
          "ObjectPath": "/Script/Engine"
        }
      },
      {
        "Type": "StructProperty",
        "Name": "K2Node_MakeStruct_ParticleSysParam_2",
        "Flags": "RF_Public",
        "ElementSize": 224,
        "Struct": {
          "ObjectName": "Class'ParticleSysParam'",
          "ObjectPath": "/Script/Engine"
        }
      },
      {
        "Type": "StructProperty",
        "Name": "CallFunc_Multiply_VectorVector_ReturnValue_3",
        "Flags": "RF_Public",
        "ElementSize": 24,
        "Struct": {
          "ObjectName": "Class'Vector'",
          "ObjectPath": "/Script/CoreUObject"
        }
      },
      {
        "Type": "StructProperty",
        "Name": "K2Node_MakeStruct_ParticleSysParam_3",
        "Flags": "RF_Public",
        "ElementSize": 224,
        "Struct": {
          "ObjectName": "Class'ParticleSysParam'",
          "ObjectPath": "/Script/Engine"
        }
      },
      {
        "Type": "StructProperty",
        "Name": "K2Node_MakeStruct_ParticleSysParam_4",
        "Flags": "RF_Public",
        "ElementSize": 224,
        "Struct": {
          "ObjectName": "Class'ParticleSysParam'",
          "ObjectPath": "/Script/Engine"
        }
      },
      {
        "Type": "StructProperty",
        "Name": "K2Node_MakeStruct_ParticleSysParam_5",
        "Flags": "RF_Public",
        "ElementSize": 224,
        "Struct": {
          "ObjectName": "Class'ParticleSysParam'",
          "ObjectPath": "/Script/Engine"
        }
      },
      {
        "Type": "StructProperty",
        "Name": "K2Node_MakeStruct_ParticleSysParam_6",
        "Flags": "RF_Public",
        "ElementSize": 224,
        "Struct": {
          "ObjectName": "Class'ParticleSysParam'",
          "ObjectPath": "/Script/Engine"
        }
      },
      {
        "Type": "ArrayProperty",
        "Name": "K2Node_MakeArray_Array",
        "Flags": "RF_Public",
        "ElementSize": 16,
        "PropertyFlags": "ReferenceParm",
        "Inner": {
          "Type": "StructProperty",
          "Name": "K2Node_MakeArray_Array",
          "Flags": "RF_Public",
          "ElementSize": 224,
          "Struct": {
            "ObjectName": "Class'ParticleSysParam'",
            "ObjectPath": "/Script/Engine"
          }
        }
      },
      {
        "Type": "BoolProperty",
        "Name": "Temp_bool_Has_Been_Initd_Variable",
        "Flags": "RF_Public",
        "ElementSize": 1,
        "FieldSize": 1,
        "ByteOffset": 0,
        "ByteMask": 1,
        "FieldMask": 255,
        "BoolSize": 1,
        "bIsNativeBool": true
      },
      {
        "Type": "BoolProperty",
        "Name": "CallFunc_IsDedicatedServer_ReturnValue",
        "Flags": "RF_Public",
        "ElementSize": 1,
        "FieldSize": 1,
        "ByteOffset": 0,
        "ByteMask": 1,
        "FieldMask": 255,
        "BoolSize": 1,
        "bIsNativeBool": true
      },
      {
        "Type": "BoolProperty",
        "Name": "Temp_bool_IsClosed_Variable",
        "Flags": "RF_Public",
        "ElementSize": 1,
        "FieldSize": 1,
        "ByteOffset": 0,
        "ByteMask": 1,
        "FieldMask": 255,
        "BoolSize": 1,
        "bIsNativeBool": true
      },
      {
        "Type": "ObjectProperty",
        "Name": "CallFunc_GetPlayerCameraManager_ReturnValue",
        "Flags": "RF_Public",
        "ElementSize": 8,
        "PropertyClass": {
          "ObjectName": "Class'PlayerCameraManager'",
          "ObjectPath": "/Script/Engine"
        }
      },
      {
        "Type": "BoolProperty",
        "Name": "CallFunc_IsValid_ReturnValue_1",
        "Flags": "RF_Public",
        "ElementSize": 1,
        "FieldSize": 1,
        "ByteOffset": 0,
        "ByteMask": 1,
        "FieldMask": 255,
        "BoolSize": 1,
        "bIsNativeBool": true
      },
      {
        "Type": "BoolProperty",
        "Name": "CallFunc_IsValid_ReturnValue_2",
        "Flags": "RF_Public",
        "ElementSize": 1,
        "FieldSize": 1,
        "ByteOffset": 0,
        "ByteMask": 1,
        "FieldMask": 255,
        "BoolSize": 1,
        "bIsNativeBool": true
      },
      {
        "Type": "StructProperty",
        "Name": "CallFunc_GetCameraLocation_ReturnValue",
        "Flags": "RF_Public",
        "ElementSize": 24,
        "Struct": {
          "ObjectName": "Class'Vector'",
          "ObjectPath": "/Script/CoreUObject"
        }
      },
      {
        "Type": "DoubleProperty",
        "Name": "Temp_real_Variable",
        "Flags": "RF_Public",
        "ElementSize": 8
      },
      {
        "Type": "StructProperty",
        "Name": "CallFunc_Subtract_VectorVector_ReturnValue",
        "Flags": "RF_Public",
        "ElementSize": 24,
        "Struct": {
          "ObjectName": "Class'Vector'",
          "ObjectPath": "/Script/CoreUObject"
        }
      },
      {
        "Type": "BoolProperty",
        "Name": "CallFunc_LessEqual_DoubleDouble_ReturnValue",
        "Flags": "RF_Public",
        "ElementSize": 1,
        "FieldSize": 1,
        "ByteOffset": 0,
        "ByteMask": 1,
        "FieldMask": 255,
        "BoolSize": 1,
        "bIsNativeBool": true
      },
      {
        "Type": "DoubleProperty",
        "Name": "CallFunc_VSize_ReturnValue",
        "Flags": "RF_Public",
        "ElementSize": 8
      },
      {
        "Type": "StructProperty",
        "Name": "CallFunc_K2_GetActorLocation_ReturnValue",
        "Flags": "RF_Public",
        "ElementSize": 24,
        "Struct": {
          "ObjectName": "Class'Vector'",
          "ObjectPath": "/Script/CoreUObject"
        }
      },
      {
        "Type": "StructProperty",
        "Name": "CallFunc_K2_GetActorLocation_ReturnValue_1",
        "Flags": "RF_Public",
        "ElementSize": 24,
        "Struct": {
          "ObjectName": "Class'Vector'",
          "ObjectPath": "/Script/CoreUObject"
        }
      },
      {
        "Type": "StructProperty",
        "Name": "CallFunc_K2_GetActorLocation_ReturnValue_2",
        "Flags": "RF_Public",
        "ElementSize": 24,
        "Struct": {
          "ObjectName": "Class'Vector'",
          "ObjectPath": "/Script/CoreUObject"
        }
      },
      {
        "Type": "ObjectProperty",
        "Name": "CallFunc_GetBuildingMeshComponent_ReturnValue",
        "Flags": "RF_Public",
        "ElementSize": 8,
        "PropertyFlags": "InstancedReference",
        "PropertyClass": {
          "ObjectName": "Class'StaticMeshComponent'",
          "ObjectPath": "/Script/Engine"
        }
      },
      {
        "Type": "StructProperty",
        "Name": "CallFunc_K2_GetComponentLocation_ReturnValue_1",
        "Flags": "RF_Public",
        "ElementSize": 24,
        "Struct": {
          "ObjectName": "Class'Vector'",
          "ObjectPath": "/Script/CoreUObject"
        }
      },
      {
        "Type": "ObjectProperty",
        "Name": "CallFunc_SpawnEmitterAtLocation_ReturnValue",
        "Flags": "RF_Public",
        "ElementSize": 8,
        "PropertyFlags": "InstancedReference",
        "PropertyClass": {
          "ObjectName": "Class'ParticleSystemComponent'",
          "ObjectPath": "/Script/Engine"
        }
      }
    ],
    "FunctionFlags": "FUNC_Final | FUNC_UbergraphFunction | FUNC_HasDefaults"
  },
  {
    "Type": "Function",
    "Name": "OnFinishedBuilding",
    "Outer": "Trap_Rail_Turret_C",
    "Class": "UScriptClass'Function'",
    "Flags": "RF_Public | RF_WasLoaded | RF_LoadCompleted",
    "SuperStruct": {
      "ObjectName": "Class'BuildingTrap:OnFinishedBuilding'",
      "ObjectPath": "/Script/FortniteGame"
    },
    "FunctionFlags": "FUNC_Event | FUNC_Public | FUNC_BlueprintEvent"
  },
  {
    "Type": "Function",
    "Name": "OnOutOfDurability",
    "Outer": "Trap_Rail_Turret_C",
    "Class": "UScriptClass'Function'",
    "Flags": "RF_Public | RF_WasLoaded | RF_LoadCompleted",
    "SuperStruct": {
      "ObjectName": "Class'BuildingTrap:OnOutOfDurability'",
      "ObjectPath": "/Script/FortniteGame"
    },
    "FunctionFlags": "FUNC_BlueprintCosmetic | FUNC_Event | FUNC_Public | FUNC_BlueprintEvent"
  },
  {
    "Type": "Function",
    "Name": "OnPlaced",
    "Outer": "Trap_Rail_Turret_C",
    "Class": "UScriptClass'Function'",
    "Flags": "RF_Public | RF_WasLoaded | RF_LoadCompleted",
    "SuperStruct": {
      "ObjectName": "Class'BuildingTrap:OnPlaced'",
      "ObjectPath": "/Script/FortniteGame"
    },
    "FunctionFlags": "FUNC_Event | FUNC_Public | FUNC_BlueprintEvent"
  },
  {
    "Type": "Function",
    "Name": "OnReloadEnd",
    "Outer": "Trap_Rail_Turret_C",
    "Class": "UScriptClass'Function'",
    "Flags": "RF_Public | RF_WasLoaded | RF_LoadCompleted",
    "SuperStruct": {
      "ObjectName": "Class'BuildingTrap:OnReloadEnd'",
      "ObjectPath": "/Script/FortniteGame"
    },
    "FunctionFlags": "FUNC_BlueprintCosmetic | FUNC_Event | FUNC_Public | FUNC_BlueprintEvent"
  },
  {
    "Type": "ParticleSystemComponent",
    "Name": "ParticleSystemComponent_3264__8797D4B5",
    "Outer": "Trap_Rail_Turret_C",
    "Class": "UScriptClass'ParticleSystemComponent'",
    "Flags": "RF_Public | RF_Transactional | RF_ArchetypeObject | RF_WasLoaded | RF_LoadCompleted",
    "Properties": {
      "Template": {
        "ObjectName": "ParticleSystem'P_Wall_Electric_Idle_01'",
        "ObjectPath": "/SaveTheWorld/Weapons/FORT_TRAPS/Wall_Electric_Trap/P_Wall_Electric_Idle_01.39"
      },
      "PrimaryComponentTick": {
        "bStartWithTickEnabled": false
      },
      "bAutoActivate": false
    }
  },
  {
    "Type": "SceneComponent",
    "Name": "Trace Location",
    "Outer": "Default__Trap_Rail_Turret_C",
    "Class": "UScriptClass'SceneComponent'",
    "Flags": "RF_Public | RF_Transactional | RF_ArchetypeObject | RF_DefaultSubObject | RF_WasLoaded | RF_LoadCompleted",
    "Properties": {
      "AttachParent": {
        "ObjectName": "BaseBuildingStaticMeshComponent'Default__Trap_Rail_Turret_C:StaticMeshComponent0'",
        "ObjectPath": "/SaveTheWorld/Items/Traps/Blueprints/Trap_Rail_Turret.2"
      },
      "RelativeLocation": {
        "X": 0.0,
        "Y": 100.0,
        "Z": 130.0
      }
    }
  },
  {
    "Type": "SceneComponent",
    "Name": "SceneComponent_66__3A5055BF",
    "Outer": "Trap_Rail_Turret_C",
    "Class": "UScriptClass'SceneComponent'",
    "Flags": "RF_Public | RF_Transactional | RF_ArchetypeObject | RF_WasLoaded | RF_LoadCompleted"
  },
  {
    "Type": "SCS_Node",
    "Name": "SCS_Node_1",
    "Outer": "SimpleConstructionScript_47",
    "Class": "UScriptClass'SCS_Node'",
    "Flags": "RF_Transactional | RF_WasLoaded | RF_LoadCompleted",
    "Properties": {
      "ComponentClass": {
        "ObjectName": "Class'ArrowComponent'",
        "ObjectPath": "/Script/Engine"
      },
      "ComponentTemplate": {
        "ObjectName": "ArrowComponent'Trap_Rail_Turret_C:ArrowComponent_0'",
        "ObjectPath": "/SaveTheWorld/Items/Traps/Blueprints/Trap_Rail_Turret.0"
      },
      "VariableGuid": "D294E9A1-CDAC4A14-42E709AD-8B744530",
      "InternalVariableName": "FireLocation"
    }
  },
  {
    "Type": "SCS_Node",
    "Name": "SCS_Node_15",
    "Outer": "SimpleConstructionScript_47",
    "Class": "UScriptClass'SCS_Node'",
    "Flags": "RF_Transactional | RF_WasLoaded | RF_LoadCompleted",
    "Properties": {
      "ComponentClass": {
        "ObjectName": "Class'StaticMeshComponent'",
        "ObjectPath": "/Script/Engine"
      },
      "ComponentTemplate": {
        "ObjectName": "StaticMeshComponent'Trap_Rail_Turret_C:StaticMeshComponent_1089__1F308B55'",
        "ObjectPath": "/SaveTheWorld/Items/Traps/Blueprints/Trap_Rail_Turret.20"
      },
      "ParentComponentOrVariableName": "StaticMeshComponent0",
      "bIsParentComponentNative": true,
      "VariableGuid": "AAC99F21-4F39C341-08DC2896-2C65587A",
      "InternalVariableName": "gun"
    }
  },
  {
    "Type": "SCS_Node",
    "Name": "SCS_Node_2",
    "Outer": "SimpleConstructionScript_47",
    "Class": "UScriptClass'SCS_Node'",
    "Flags": "RF_Transactional | RF_WasLoaded | RF_LoadCompleted",
    "Properties": {
      "ComponentClass": {
        "ObjectName": "Class'ParticleSystemComponent'",
        "ObjectPath": "/Script/Engine"
      },
      "ComponentTemplate": {
        "ObjectName": "ParticleSystemComponent'Trap_Rail_Turret_C:ParticleSystemComponent_3264__8797D4B5'",
        "ObjectPath": "/SaveTheWorld/Items/Traps/Blueprints/Trap_Rail_Turret.10"
      },
      "VariableGuid": "76CDB183-5752BAA6-B08DE4CC-D0596031",
      "InternalVariableName": "Effect_Charge"
    }
  },
  {
    "Type": "SCS_Node",
    "Name": "SCS_Node_5",
    "Outer": "SimpleConstructionScript_47",
    "Class": "UScriptClass'SCS_Node'",
    "Flags": "RF_Transactional | RF_WasLoaded | RF_LoadCompleted",
    "Properties": {
      "ComponentClass": {
        "ObjectName": "Class'BoxComponent'",
        "ObjectPath": "/Script/Engine"
      },
      "ComponentTemplate": {
        "ObjectName": "BoxComponent'Trap_Rail_Turret_C:BoxComponent_126__FC5252EC'",
        "ObjectPath": "/SaveTheWorld/Items/Traps/Blueprints/Trap_Rail_Turret.4"
      },
      "VariableGuid": "8F7CD171-28175AA6-0DAF855B-6358BC50",
      "InternalVariableName": "TriggerComponent"
    }
  },
  {
    "Type": "SCS_Node",
    "Name": "SCS_Node_6",
    "Outer": "SimpleConstructionScript_47",
    "Class": "UScriptClass'SCS_Node'",
    "Flags": "RF_Transactional | RF_WasLoaded | RF_LoadCompleted",
    "Properties": {
      "ComponentClass": {
        "ObjectName": "Class'SceneComponent'",
        "ObjectPath": "/Script/Engine"
      },
      "ComponentTemplate": {
        "ObjectName": "SceneComponent'Trap_Rail_Turret_C:SceneComponent_66__3A5055BF'",
        "ObjectPath": "/SaveTheWorld/Items/Traps/Blueprints/Trap_Rail_Turret.12"
      },
      "ParentComponentOrVariableName": "StaticMeshComponent0",
      "bIsParentComponentNative": true,
      "ChildNodes": [
        {
          "ObjectName": "SCS_Node'Trap_Rail_Turret_C:SimpleConstructionScript_47.SCS_Node_5'",
          "ObjectPath": "/SaveTheWorld/Items/Traps/Blueprints/Trap_Rail_Turret.16"
        },
        {
          "ObjectName": "SCS_Node'Trap_Rail_Turret_C:SimpleConstructionScript_47.SCS_Node_2'",
          "ObjectPath": "/SaveTheWorld/Items/Traps/Blueprints/Trap_Rail_Turret.15"
        },
        {
          "ObjectName": "SCS_Node'Trap_Rail_Turret_C:SimpleConstructionScript_47.SCS_Node_1'",
          "ObjectPath": "/SaveTheWorld/Items/Traps/Blueprints/Trap_Rail_Turret.13"
        }
      ],
      "VariableGuid": "D043A935-05A0EDF2-BFB3C70F-D156AFD6",
      "InternalVariableName": "Root"
    }
  },
  {
    "Type": "SCS_Node",
    "Name": "SCS_Node_687",
    "Outer": "SimpleConstructionScript_47",
    "Class": "UScriptClass'SCS_Node'",
    "Flags": "RF_Transactional | RF_WasLoaded | RF_LoadCompleted",
    "Properties": {
      "ComponentClass": {
        "ObjectName": "Class'SceneComponent'",
        "ObjectPath": "/Script/Engine"
      },
      "ComponentTemplate": null,
      "VariableGuid": "56BC9799-C494E6E6-321D4295-7D5EB316",
      "InternalVariableName": "DefaultSceneRoot"
    }
  },
  {
    "Type": "SimpleConstructionScript",
    "Name": "SimpleConstructionScript_47",
    "Outer": "Trap_Rail_Turret_C",
    "Class": "UScriptClass'SimpleConstructionScript'",
    "Flags": "RF_Transactional | RF_WasLoaded | RF_LoadCompleted",
    "Properties": {
      "RootNodes": [
        {
          "ObjectName": "SCS_Node'Trap_Rail_Turret_C:SimpleConstructionScript_47.SCS_Node_15'",
          "ObjectPath": "/SaveTheWorld/Items/Traps/Blueprints/Trap_Rail_Turret.14"
        },
        {
          "ObjectName": "SCS_Node'Trap_Rail_Turret_C:SimpleConstructionScript_47.SCS_Node_6'",
          "ObjectPath": "/SaveTheWorld/Items/Traps/Blueprints/Trap_Rail_Turret.17"
        }
      ],
      "AllNodes": [
        {
          "ObjectName": "SCS_Node'Trap_Rail_Turret_C:SimpleConstructionScript_47.SCS_Node_15'",
          "ObjectPath": "/SaveTheWorld/Items/Traps/Blueprints/Trap_Rail_Turret.14"
        },
        {
          "ObjectName": "SCS_Node'Trap_Rail_Turret_C:SimpleConstructionScript_47.SCS_Node_6'",
          "ObjectPath": "/SaveTheWorld/Items/Traps/Blueprints/Trap_Rail_Turret.17"
        },
        {
          "ObjectName": "SCS_Node'Trap_Rail_Turret_C:SimpleConstructionScript_47.SCS_Node_5'",
          "ObjectPath": "/SaveTheWorld/Items/Traps/Blueprints/Trap_Rail_Turret.16"
        },
        {
          "ObjectName": "SCS_Node'Trap_Rail_Turret_C:SimpleConstructionScript_47.SCS_Node_2'",
          "ObjectPath": "/SaveTheWorld/Items/Traps/Blueprints/Trap_Rail_Turret.15"
        },
        {
          "ObjectName": "SCS_Node'Trap_Rail_Turret_C:SimpleConstructionScript_47.SCS_Node_1'",
          "ObjectPath": "/SaveTheWorld/Items/Traps/Blueprints/Trap_Rail_Turret.13"
        }
      ],
      "DefaultSceneRootNode": {
        "ObjectName": "SCS_Node'Trap_Rail_Turret_C:SimpleConstructionScript_47.SCS_Node_687'",
        "ObjectPath": "/SaveTheWorld/Items/Traps/Blueprints/Trap_Rail_Turret.18"
      }
    }
  },
  {
    "Type": "StaticMeshComponent",
    "Name": "StaticMeshComponent_1089__1F308B55",
    "Outer": "Trap_Rail_Turret_C",
    "Class": "UScriptClass'StaticMeshComponent'",
    "Flags": "RF_Public | RF_Transactional | RF_ArchetypeObject | RF_WasLoaded | RF_LoadCompleted",
    "Properties": {
      "StaticMesh": {
        "ObjectName": "StaticMesh'S_Trap_CoolDown_Clock'",
        "ObjectPath": "/SaveTheWorld/Weapons/FORT_TRAPS/General/S_Trap_CoolDown_Clock.1"
      },
      "BodyInstance": {
        "bAutoWeld": false
      },
      "RelativeLocation": {
        "X": 0.0,
        "Y": 50.0,
        "Z": 130.0
      },
      "RelativeScale3D": {
        "X": 2.0,
        "Y": 10.0,
        "Z": 2.0
      }
    }
  },
  {
    "Type": "Trap_Rail_Turret_C",
    "Name": "Default__Trap_Rail_Turret_C",
    "Class": "BlueprintGeneratedClass'/SaveTheWorld/Items/Traps/Blueprints/Trap_Rail_Turret.Trap_Rail_Turret_C'",
    "Flags": "RF_Public | RF_ClassDefaultObject | RF_ArchetypeObject | RF_WasLoaded | RF_LoadCompleted",
    "Properties": {
      "UberGraphFrame": {},
      "Activate_Sound_Cue": {
        "ObjectName": "SoundCue'Wall_Electric_Trap_Ready'",
        "ObjectPath": "/SaveTheWorld/Sounds/Fort_Traps/Wall_Electric/Wall_Electric_Trap_Ready.0"
      },
      "Explode_Sound_Cue": {
        "ObjectName": "SoundCue'Wall_Electric_Trap_Explode'",
        "ObjectPath": "/SaveTheWorld/Sounds/Fort_Traps/Wall_Electric/Wall_Electric_Trap_Explode.0"
      },
      "TraceLocation": {
        "ObjectName": "SceneComponent'Default__Trap_Rail_Turret_C:Trace Location'",
        "ObjectPath": "/SaveTheWorld/Items/Traps/Blueprints/Trap_Rail_Turret.11"
      },
      "TrapRangeMesh": {
        "ObjectName": "StaticMesh'S_Trap_Wall_Electric_Wall_Guide'",
        "ObjectPath": "/SaveTheWorld/Weapons/FORT_TRAPS/Wall_Electric_Trap/S_Trap_Wall_Electric_Wall_Guide.1"
      },
      "AbilitySet": {
        "ObjectName": "FortAbilitySet'GAS_Trap_RailTurret'",
        "ObjectPath": "/SaveTheWorld/Abilities/Traps/RailTurret/GAS_Trap_RailTurret.0"
      },
      "StimSourceComponent": {
        "ObjectName": "AthenaTrapAIPerceptionStimuliSourceComponent'Default__Trap_Rail_Turret_C:Trap AI Perception Stimuli Source Component'",
        "ObjectPath": "/SaveTheWorld/Items/Traps/Blueprints/Trap_Rail_Turret.1"
      },
      "StaticMesh": {
        "ObjectName": "StaticMesh'Electric_Trap_Wall'",
        "ObjectPath": "/SaveTheWorld/Weapons/FORT_TRAPS/Wall_Electric_Trap/Mesh/Electric_Trap_Wall.1"
      },
      "StaticMeshComponent": {
        "ObjectName": "BaseBuildingStaticMeshComponent'Default__Trap_Rail_Turret_C:StaticMeshComponent0'",
        "ObjectPath": "/SaveTheWorld/Items/Traps/Blueprints/Trap_Rail_Turret.2"
      },
      "bIsDynamicOnDedicatedServer": true,
      "RootComponent": {
        "ObjectName": "BaseBuildingStaticMeshComponent'Default__Trap_Rail_Turret_C:StaticMeshComponent0'",
        "ObjectPath": "/SaveTheWorld/Items/Traps/Blueprints/Trap_Rail_Turret.2"
      }
    },
    "SerializedSparseClassDataStruct": "UScriptClass'BuildingTrapActorClassData'",
    "SerializedSparseClassData": {
      "bBlocksAttachmentPlacement": true,
      "AttributeInitKeys": {
        "AttributeInitCategory": "BuildingDeco",
        "AttributeInitSubCategory": "1"
      },
      "AttributeInitKeys[1]": {
        "AttributeInitCategory": "BuildingDeco",
        "AttributeInitSubCategory": "1"
      },
      "NavigationLinkSoftClass": {
        "AssetPathName": "",
        "SubPathString": ""
      }
    }
  }
]