[
  {
    "Type": "FortQuestDefinitionComponent_DisplaySettings",
    "Name": "FortQuestDefinitionComponent_DisplaySettings_0",
    "Outer": "Wargames_Quest_Wargame_Tprifts",
    "Class": "UScriptClass'FortQuestDefinitionComponent_DisplaySettings'",
    "Flags": "RF_Transactional | RF_WasLoaded | RF_LoadCompleted",
    "Properties": {
      "InformationSettings": {
        "CompletionText": {
          "Namespace": "",
          "Key": "A53D8EB54ED0AB13650CDBB31D5FD13A",
          "SourceString": "\"Shortcut\" completed!",
          "LocalizedString": "\"Shortcut\" completed!"
        }
      }
    }
  },
  {
    "Type": "FortQuestItemDefinition_Campaign",
    "Name": "Wargames_Quest_Wargame_Tprifts",
    "Class": "UScriptClass'FortQuestItemDefinition_Campaign'",
    "Flags": "RF_Public | RF_Standalone | RF_Transactional | RF_WasLoaded | RF_LoadCompleted",
    "Properties": {
      "QuestType": "EFortQuestType::Optional",
      "RewardsTable": {
        "ObjectName": "DataTable'QuestRewards'",
        "ObjectPath": "/Game/Quests/QuestRewards.0"
      },
      "Objectives": [
        {
          "BackendName": "wargames_play_wargame_tprifts",
          "ItemEvent": "EFortQuestObjectiveItemEvent::Max_None",
          "bHidden": false,
          "bRequirePrimaryMissionCompletion": false,
          "bCanProgressInZone": true,
          "bDisplayDynamicAnnouncementUpdate": true,
          "DynamicStatusUpdateType": "EObjectiveStatusUpdateType::OnComplete",
          "LinkToItemManagement": "EFortFrontendInventoryFilter::Max_None",
          "ObjectiveFilters": [],
          "InlineObjectiveStats": [],
          "ObjectiveStatHandle": {
            "DataTable": {
              "ObjectName": "DataTable'ObjectiveStatTable'",
              "ObjectPath": "/Game/Quests/ObjectiveStatTable.0"
            },
            "RowName": "wargames_play_wargame_tprifts"
          },
          "AlternativeStatHandles": [],
          "ItemReference": {
            "AssetPathName": "",
            "SubPathString": ""
          },
          "ItemTemplateIdOverride": "",
          "LinkSquadID": "None",
          "LinkSquadIndex": 0,
          "Description": {
            "Namespace": "",
            "Key": "44F0D8ED49E530719BD5E1A8283AEAA7",
            "SourceString": "Complete the \"Shortcut\" Wargames Simulation",
            "LocalizedString": "Complete the \"Shortcut\" Wargames Simulation"
          },
          "HudShortDescription": {
            "Namespace": "",
            "Key": "8DC2F4714C554F00F43833A0351EFB32",
            "SourceString": "\"Shortcut\" Wargames Simulation completed",
            "LocalizedString": "\"Shortcut\" Wargames Simulation completed"
          },
          "ObjectiveConversations": [],
          "ObjectiveDisplayInfo": {
            "DisplayStage": 0,
            "DisplayMaxStage": 0
          },
          "Count": 1,
          "Stage": -1,
          "DynamicStatusUpdatePercentInterval": 25,
          "DynamicUpdateCompletionDelay": 0.0,
          "ScriptedAction": {
            "AssetPathName": "",
            "SubPathString": ""
          },
          "FrontendScriptedAction": {
            "AssetPathName": "",
            "SubPathString": ""
          }
        }
      ],
      "Category": {
        "DataTable": {
          "ObjectName": "DataTable'QuestCategoryTable'",
          "ObjectPath": "/Game/Quests/QuestCategoryTable.0"
        },
        "RowName": "LTE_Season9Wargames"
      },
      "SortPriority": 60,
      "QuestDefinitionComponents": [
        {
          "ObjectName": "FortQuestDefinitionComponent_DisplaySettings'Wargames_Quest_Wargame_Tprifts:FortQuestDefinitionComponent_DisplaySettings_0'",
          "ObjectPath": "/SaveTheWorld/Quests/Outpost/Wargames/BootCamp/Simulations/Wargames_Quest_Wargame_Tprifts.0"
        }
      ],
      "ItemName": {
        "Namespace": "",
        "Key": "8F8D303D4C39863A686B7B98FA2425C5",
        "SourceString": "Simulation: \"Shortcut\"",
        "LocalizedString": "Simulation: \"Shortcut\""
      },
      "ItemDescription": {
        "Namespace": "",
        "Key": "1209A23C4111CB29691E3686E21A3F08",
        "SourceString": "Complete the \"Shortcut\" Wargames Simulation. \r\n\r\nAccess Wargames from the Computer in your Storm Shield or by assisting other players via Community Lookout!",
        "LocalizedString": "Complete the \"Shortcut\" Wargames Simulation. \r\n\r\nAccess Wargames from the Computer in your Storm Shield or by assisting other players via Community Lookout!"
      },
      "DataList": [
        {
          "Icon": {
            "AssetPathName": "/SaveTheWorld/UI/Foundation/Textures/Icons/Mission/T-Icons-TeleportationRiftsNoFrame-128.T-Icons-TeleportationRiftsNoFrame-128",
            "SubPathString": ""
          }
        }
      ]
    }
  }
]