[
  {
    "Type": "FortQuestDefinitionComponent_DisplaySettings",
    "Name": "FortQuestDefinitionComponent_DisplaySettings_0",
    "Outer": "Wargames_Quest_Wargame_Telebomb",
    "Class": "UScriptClass'FortQuestDefinitionComponent_DisplaySettings'",
    "Flags": "RF_Transactional | RF_WasLoaded | RF_LoadCompleted",
    "Properties": {
      "InformationSettings": {
        "CompletionText": {
          "Namespace": "",
          "Key": "52ABED2F4056F62B5FFB57A6B6E8A834",
          "SourceString": "\"Quantum Countdown\" completed!",
          "LocalizedString": "\"Quantum Countdown\" completed!"
        }
      }
    }
  },
  {
    "Type": "FortQuestItemDefinition_Campaign",
    "Name": "Wargames_Quest_Wargame_Telebomb",
    "Class": "UScriptClass'FortQuestItemDefinition_Campaign'",
    "Flags": "RF_Public | RF_Standalone | RF_Transactional | RF_WasLoaded | RF_LoadCompleted",
    "Properties": {
      "QuestType": "EFortQuestType::Optional",
      "RewardsTable": {
        "ObjectName": "DataTable'QuestRewards'",
        "ObjectPath": "/Game/Quests/QuestRewards.0"
      },
      "Objectives": [
        {
          "BackendName": "wargames_play_wargame_telebomb",
          "ItemEvent": "EFortQuestObjectiveItemEvent::Max_None",
          "bHidden": false,
          "bRequirePrimaryMissionCompletion": false,
          "bCanProgressInZone": true,
          "bDisplayDynamicAnnouncementUpdate": true,
          "DynamicStatusUpdateType": "EObjectiveStatusUpdateType::OnComplete",
          "LinkToItemManagement": "EFortFrontendInventoryFilter::Max_None",
          "ObjectiveFilters": [],
          "InlineObjectiveStats": [],
          "ObjectiveStatHandle": {
            "DataTable": {
              "ObjectName": "DataTable'ObjectiveStatTable'",
              "ObjectPath": "/Game/Quests/ObjectiveStatTable.0"
            },
            "RowName": "wargames_play_wargame_telebomb"
          },
          "AlternativeStatHandles": [],
          "ItemReference": {
            "AssetPathName": "",
            "SubPathString": ""
          },
          "ItemTemplateIdOverride": "",
          "LinkSquadID": "None",
          "LinkSquadIndex": 0,
          "Description": {
            "Namespace": "",
            "Key": "EE452E39429663036D0793A017CE9FA8",
            "SourceString": "Complete the \"Quantum Countdown\" Wargames Simulation",
            "LocalizedString": "Complete the \"Quantum Countdown\" Wargames Simulation"
          },
          "HudShortDescription": {
            "Namespace": "",
            "Key": "3987FD7443AAF2BD86926C9E923D96F7",
            "SourceString": "\"Quantum Countdown\" Wargames Simulation completed",
            "LocalizedString": "\"Quantum Countdown\" Wargames Simulation completed"
          },
          "ObjectiveConversations": [],
          "ObjectiveDisplayInfo": {
            "DisplayStage": 0,
            "DisplayMaxStage": 0
          },
          "Count": 1,
          "Stage": -1,
          "DynamicStatusUpdatePercentInterval": 25,
          "DynamicUpdateCompletionDelay": 0.0,
          "ScriptedAction": {
            "AssetPathName": "",
            "SubPathString": ""
          },
          "FrontendScriptedAction": {
            "AssetPathName": "",
            "SubPathString": ""
          }
        }
      ],
      "Category": {
        "DataTable": {
          "ObjectName": "DataTable'QuestCategoryTable'",
          "ObjectPath": "/Game/Quests/QuestCategoryTable.0"
        },
        "RowName": "LTE_Season9Wargames"
      },
      "SortPriority": 60,
      "QuestDefinitionComponents": [
        {
          "ObjectName": "FortQuestDefinitionComponent_DisplaySettings'Wargames_Quest_Wargame_Telebomb:FortQuestDefinitionComponent_DisplaySettings_0'",
          "ObjectPath": "/SaveTheWorld/Quests/Outpost/Wargames/BootCamp/Simulations/Wargames_Quest_Wargame_Telebomb.0"
        }
      ],
      "ItemName": {
        "Namespace": "",
        "Key": "4D56324F484C1FE1D9B28BB81593B565",
        "SourceString": "Simulation: \"Quantum Countdown\"",
        "LocalizedString": "Simulation: \"Quantum Countdown\""
      },
      "ItemDescription": {
        "Namespace": "",
        "Key": "2CB6DE63487C6736737F4F9660F54E72",
        "SourceString": "Complete the \"Quantum Countdown\" Wargames Simulation. \r\n\r\nAccess Wargames from the Computer in your Storm Shield or by assisting other players via Community Lookout!",
        "LocalizedString": "Complete the \"Quantum Countdown\" Wargames Simulation. \r\n\r\nAccess Wargames from the Computer in your Storm Shield or by assisting other players via Community Lookout!"
      },
      "DataList": [
        {
          "Icon": {
            "AssetPathName": "/SaveTheWorld/UI/Foundation/Textures/Icons/Mission/T-Icons-TeleportingBombNoFrame-128.T-Icons-TeleportingBombNoFrame-128",
            "SubPathString": ""
          }
        }
      ]
    }
  }
]